{
  "import { ui } from './test-utils'": {
    "body": "import { ui } from './test-utils'",
    "prefix": "ui"
  },
  "taglog": {
    "body": "log(`\\${tag}$1`, style, $2)",
    "prefix": "taglog"
  },
  "test": {
    "body": [
      "import { expect } from 'chai'",
      "import * as u from '@jsmanifest/utils'",
      "import * as nc from 'noodl-common'",
      "import * as nt from 'noodl-types'",
      "import * as nu from 'noodl-utils'",
      "import { ui } from './test-utils'",
      "$1",
      "",
      "describe(nc.coolGold(`$2`), () => {",
      "  xit(nc.italic(`$3`), () => {",
      "    $4",
      "  })",
      "})",
      ""
    ],
    "prefix": "test"
  },
  "userEvent": {
    "body": "import userEvent from '@testing-library/user-event'",
    "prefix": "userevent"
  }
}
